DAY5/counter4.v
module counter4 (
    input clk,
    input reset,
    output reg [3:0] count
);

always @(posedge clk) begin

    if (reset)
        count <= 4'b0000;
    else
        count <= count + 1'b1;

end

endmodule

DAY5/tb_counter4.v
`timescale 1ns/1ps

module tb_counter4;

reg clk;
reg reset;

wire [3:0] count;

counter4 uut (
    .clk(clk),
    .reset(reset),
    .count(count)
);

initial begin
    clk = 0;

    forever #5 clk = ~clk;
end

initial begin

    $dumpfile("counter4.vcd");
    $dumpvars(0, tb_counter4);

    reset = 1;
    #12;

    reset = 0;
    #100;

    $finish;

end

endmodule

DAY5/counter4.vcd
$date
	Fri Sep 04 14:55:36 2026
$end
$version
	Icarus Verilog
$end
$timescale
	1ps
$end
$scope module tb_counter4 $end
$var wire 4 ! count [3:0] $end
$var reg 1 " clk $end
$var reg 1 # reset $end
$scope module uut $end
$var wire 1 " clk $end
$var wire 1 # reset $end
$var reg 4 $ count [3:0] $end
$upscope $end
$upscope $end
$enddefinitions $end
$comment Show the parameter values. $end
$dumpall
$end
#0
$dumpvars
bx $
1#
0"
bx !
$end
#5000
b0 !
b0 $
1"
#10000
0"
#12000
0#
#15000
b1 !
b1 $
1"
#20000
0"
#25000
b10 !
b10 $
1"
#30000
0"
#35000
b11 !
b11 $
1"
#40000
0"
#45000
b100 !
b100 $
1"
#50000
0"
#55000
b101 !
b101 $
1"
#60000
0"
#65000
b110 !
b110 $
1"
#70000
0"
#75000
b111 !
b111 $
1"
#80000
0"
#85000
b1000 !
b1000 $
1"
#90000
0"
#95000
b1001 !
b1001 $
1"
#100000
0"
#105000
b1010 !
b1010 $
1"
