DAY5/dff.v
module dff (
    input  clk,
    input  d,
    output reg q
);

always @(posedge clk) begin
    q <= d;
end

endmodule

DAY5/tb_dff.v
`timescale 1ns/1ps

module tb_dff;

reg clk;
reg d;

wire q;

dff uut (
    .clk(clk),
    .d(d),
    .q(q)
);

initial begin
    clk = 0;

    forever #5 clk = ~clk;
end

initial begin

    $dumpfile("dff.vcd");
    $dumpvars(0, tb_dff);

    d = 0;
    #12;

    d = 1;
    #10;

    d = 0;
    #10;

    d = 1;
    #10;

    $finish;

end

endmodule

DAY5/dff.vcd
$date
	Fri Sep 04 13:24:46 2026
$end
$version
	Icarus Verilog
$end
$timescale
	1ps
$end
$scope module tb_dff $end
$var wire 1 ! q $end
$var reg 1 " clk $end
$var reg 1 # d $end
$scope module uut $end
$var wire 1 " clk $end
$var wire 1 # d $end
$var reg 1 ! q $end
$upscope $end
$upscope $end
$enddefinitions $end
$comment Show the parameter values. $end
$dumpall
$end
#0
$dumpvars
0#
0"
x!
$end
#5000
0!
1"
#10000
0"
#12000
1#
#15000
1!
1"
#20000
0"
#22000
0#
#25000
0!
1"
#30000
0"
#32000
1#
#35000
1!
1"
