DAY1/mux2/mux8x1.v
`timescale 1ns/1ps

module mux8x1 (
    input [7:0] d,      // 8 data inputs (d[0] to d[7])
    input [2:0] s,      // 3 select lines (s[0] to s[2])
    output reg y        // 1 output
);

    // The always block triggers whenever a data input or select line changes
    always @(*) begin
        case (s)
            3'b000: y = d[0];
            3'b001: y = d[1];
            3'b010: y = d[2];
            3'b011: y = d[3];
            3'b100: y = d[4];
            3'b101: y = d[5];
            3'b110: y = d[6];
            3'b111: y = d[7];
            default: y = 1'b0; 
        endcase
    end

endmodule

DAY1/mux2/tb_mux8x1.v
`timescale 1ns/1ps

module tb_mux8x1;

    // Inputs are registers
    reg [7:0] d;
    reg [2:0] s;
    
    // Output is a wire
    wire y;

    // Instantiate the 8:1 MUX
    mux8x1 uut (
        .d(d),
        .s(s),
        .y(y)
    );

    initial begin
        // Generate the VCD file for GTKWave
        $dumpfile("mux8x1.vcd");
        $dumpvars(0, tb_mux8x1);

        // Set a fixed pattern for the data inputs: 10101010
        // d[7]=1, d[6]=0, d[5]=1, d[4]=0, d[3]=1, d[2]=0, d[1]=1, d[0]=0
        d = 8'b10101010; 
        
        // Test all select line combinations
        s = 3'b000; #10; // Should output d[0] (0)
        s = 3'b001; #10; // Should output d[1] (1)
        s = 3'b010; #10; // Should output d[2] (0)
        s = 3'b011; #10; // Should output d[3] (1)
        s = 3'b100; #10; // Should output d[4] (0)
        s = 3'b101; #10; // Should output d[5] (1)
        s = 3'b110; #10; // Should output d[6] (0)
        s = 3'b111; #10; // Should output d[7] (1)

        $finish;
    end

endmodule

DAY1/mux2/mux8x1.vcd
$date
	Sun Aug 16 13:52:30 2026
$end
$version
	Icarus Verilog
$end
$timescale
	1ps
$end
$scope module tb_mux8x1 $end
$var wire 1 ! y $end
$var reg 8 " d [7:0] $end
$var reg 3 # s [2:0] $end
$scope module uut $end
$var wire 8 $ d [7:0] $end
$var wire 3 % s [2:0] $end
$var reg 1 ! y $end
$upscope $end
$upscope $end
$enddefinitions $end
$comment Show the parameter values. $end
$dumpall
$end
#0
$dumpvars
b0 %
b10101010 $
b0 #
b10101010 "
0!
$end
#10000
1!
b1 #
b1 %
#20000
0!
b10 #
b10 %
#30000
1!
b11 #
b11 %
#40000
0!
b100 #
b100 %
#50000
1!
b101 #
b101 %
#60000
0!
b110 #
b110 %
#70000
1!
b111 #
b111 %
